color_code_stim/__init__.py
color_code_stim/circuit_builder.py
color_code_stim/color_code.py
color_code_stim/config.py
color_code_stim/cultivation.py
color_code_stim/graph_builder.py
color_code_stim/noise_model.py
color_code_stim/stim_symbolic.py
color_code_stim/stim_utils.py
color_code_stim/utils.py
color_code_stim/visualization.py
color_code_stim/assets/cultivation_circuits/README.md
color_code_stim/assets/cultivation_circuits/d3_p0.0005.stim
color_code_stim/assets/cultivation_circuits/d3_p0.001.stim
color_code_stim/assets/cultivation_circuits/d3_p0.001.svg
color_code_stim/assets/cultivation_circuits/d3_p0.stim
color_code_stim/assets/cultivation_circuits/d5_p0.0001.stim
color_code_stim/assets/cultivation_circuits/d5_p0.0005.stim
color_code_stim/assets/cultivation_circuits/d5_p0.001.stim
color_code_stim/assets/cultivation_circuits/d5_p0.001.svg
color_code_stim/assets/cultivation_circuits/d5_p0.stim
color_code_stim/assets/cultivation_circuits/d5_p1e-05.stim
color_code_stim/decoders/__init__.py
color_code_stim/decoders/base.py
color_code_stim/decoders/belief_concat_matching_decoder.py
color_code_stim/decoders/bp_decoder.py
color_code_stim/decoders/concat_matching_decoder.py
color_code_stim/dem_utils/__init__.py
color_code_stim/dem_utils/dem_decomp.py
color_code_stim/dem_utils/dem_manager.py
color_code_stim/simulation/__init__.py
color_code_stim/simulation/sampling_utils.py
color_code_stim/simulation/simulator.py
color_code_stim-1.1.1.dist-info/licenses/LICENSE
color_code_stim-1.1.1.dist-info/METADATA
color_code_stim-1.1.1.dist-info/WHEEL
color_code_stim-1.1.1.dist-info/top_level.txt
color_code_stim-1.1.1.dist-info/RECORD
