Metadata-Version: 2.4
Name: color-code-stim
Version: 1.1.1
Summary: A small Python module for simulating & decoding 2D color code circuits
Author-email: Seok-Hyung Lee <sh.lee1524@gmail.com>
License: MIT
Project-URL: Homepage, https://github.com/seokhyung-lee/color-code-stim
Project-URL: Bug Tracker, https://github.com/seokhyung-lee/color-code-stim/issues
Classifier: Programming Language :: Python :: 3
Classifier: License :: OSI Approved :: MIT License
Classifier: Operating System :: OS Independent
Classifier: Intended Audience :: Science/Research
Classifier: Topic :: Scientific/Engineering :: Physics
Requires-Python: >=3.11
License-File: LICENSE
Requires-Dist: numpy>=1.23.5
Requires-Dist: matplotlib>=3.7.1
Requires-Dist: stim>=1.14.0
Requires-Dist: pymatching>=2.1.0
Requires-Dist: python-igraph>=0.11.3
Requires-Dist: statsmodels>=0.14.1
Requires-Dist: cairosvg>=2.8.0
Requires-Dist: jupyter
Requires-Dist: pytest
Dynamic: license-file
